<?xml version="1.0" encoding="UTF-8"?>
<!DOCTYPE mapper PUBLIC "-//mybatis.org//DTD Mapper 3.0//EN" "http://mybatis.org/dtd/mybatis-3-mapper.dtd">
<mapper namespace="com.mogoroom.service.acct.dao.AccountMapper">
  <resultMap id="BaseResultMap" type="com.mogoroom.service.acct.domain.Account">
    <id column="id" jdbcType="INTEGER" property="id" />
    <result column="acctId" jdbcType="INTEGER" property="acctId" />
    <result column="wjIdentity" jdbcType="VARCHAR" property="wjIdentity" />
    <result column="createTime" jdbcType="TIMESTAMP" property="createTime" />
    <result column="updateTime" jdbcType="TIMESTAMP" property="updateTime" />
    <result column="userId" jdbcType="INTEGER" property="userId" />
    <result column="userType" jdbcType="TINYINT" property="userType" />
  </resultMap>
  <sql id="Base_Column_List">
    id, acctId, wjIdentity, createTime, updateTime, userId, userType
  </sql>
  <select id="selectById" parameterType="java.lang.Integer" resultMap="BaseResultMap">
    select 
    <include refid="Base_Column_List" />
    from acct_account
    where id = #{id,jdbcType=INTEGER}
  </select>
  <delete id="delete" parameterType="java.lang.Integer">
    delete from acct_account
    where id = #{id,jdbcType=INTEGER}
  </delete>
  <insert id="insert" keyProperty="id" parameterType="com.mogoroom.service.acct.domain.Account" useGeneratedKeys="true">
    insert into acct_account
    <trim prefix="(" suffix=")" suffixOverrides=",">
      <if test="acctId != null">
        acctId,
      </if>
      <if test="wjIdentity != null">
        wjIdentity,
      </if>
      <if test="createTime != null">
        createTime,
      </if>
      <if test="updateTime != null">
        updateTime,
      </if>
      <if test="userId != null">
        userId,
      </if>
      <if test="userType != null">
        userType,
      </if>
    </trim>
    <trim prefix="values (" suffix=")" suffixOverrides=",">
      <if test="acctId != null">
        #{acctId,jdbcType=INTEGER},
      </if>
      <if test="wjIdentity != null">
        #{wjIdentity,jdbcType=VARCHAR},
      </if>
      <if test="createTime != null">
        #{createTime,jdbcType=TIMESTAMP},
      </if>
      <if test="updateTime != null">
        #{updateTime,jdbcType=TIMESTAMP},
      </if>
      <if test="userId != null">
        #{userId,jdbcType=INTEGER},
      </if>
      <if test="userType != null">
        #{userType,jdbcType=TINYINT},
      </if>
    </trim>
  </insert>
  <update id="update" parameterType="com.mogoroom.service.acct.domain.Account">
    update acct_account
    <set>
      <if test="acctId != null">
        acctId = #{acctId,jdbcType=INTEGER},
      </if>
      <if test="wjIdentity != null">
        wjIdentity = #{wjIdentity,jdbcType=VARCHAR},
      </if>
      <if test="createTime != null">
        createTime = #{createTime,jdbcType=TIMESTAMP},
      </if>
      <if test="updateTime != null">
        updateTime = #{updateTime,jdbcType=TIMESTAMP},
      </if>
      <if test="userId != null">
        userId = #{userId,jdbcType=INTEGER},
      </if>
      <if test="userType != null">
        userType = #{userType,jdbcType=TINYINT},
      </if>
    </set>
    where id = #{id,jdbcType=INTEGER}
  </update>
  <select id="selectAll" resultMap="BaseResultMap">
    select
    <include refid="Base_Column_List" />
    from acct_account
  </select>

  <select id="selectListPageInfo" parameterType="map" resultMap="BaseResultMap">
    select
    <include refid="Base_Column_List" />
    from acct_account
	where 1=1
	    <if test="po.id != null">
          and id = #{po.id,jdbcType=INTEGER}
    </if>
    <if test="po.acctId != null">
          and acctId = #{po.acctId,jdbcType=INTEGER}
    </if>
    <if test="po.wjIdentity != null">
          and wjIdentity = #{po.wjIdentity,jdbcType=VARCHAR}
    </if>
    <if test="po.createTime != null">
          and createTime = #{po.createTime,jdbcType=TIMESTAMP}
    </if>
    <if test="po.updateTime != null">
          and updateTime = #{po.updateTime,jdbcType=TIMESTAMP}
    </if>
    <if test="po.userId != null">
          and userId = #{po.userId,jdbcType=INTEGER}
    </if>
    <if test="po.userType != null">
          and userType = #{po.userType,jdbcType=TINYINT}
    </if>

  </select>
  <resultMap id="BaseResultMap" type="com.mogoroom.service.acct.domain.Account">
    <id column="id" jdbcType="INTEGER" property="id" />
    <result column="acctId" jdbcType="INTEGER" property="acctId" />
    <result column="wjIdentity" jdbcType="VARCHAR" property="wjIdentity" />
    <result column="createTime" jdbcType="TIMESTAMP" property="createTime" />
    <result column="updateTime" jdbcType="TIMESTAMP" property="updateTime" />
    <result column="userId" jdbcType="INTEGER" property="userId" />
    <result column="userType" jdbcType="TINYINT" property="userType" />
  </resultMap>
  <sql id="Base_Column_List">
    id, acctId, wjIdentity, createTime, updateTime, userId, userType
  </sql>
  <select id="selectById" parameterType="java.lang.Integer" resultMap="BaseResultMap">
    select 
    <include refid="Base_Column_List" />
    from acct_account
    where id = #{id,jdbcType=INTEGER}
  </select>
  <delete id="delete" parameterType="java.lang.Integer">
    delete from acct_account
    where id = #{id,jdbcType=INTEGER}
  </delete>
  <insert id="insert" keyProperty="id" parameterType="com.mogoroom.service.acct.domain.Account" useGeneratedKeys="true">
    insert into acct_account
    <trim prefix="(" suffix=")" suffixOverrides=",">
      <if test="acctId != null">
        acctId,
      </if>
      <if test="wjIdentity != null">
        wjIdentity,
      </if>
      <if test="createTime != null">
        createTime,
      </if>
      <if test="updateTime != null">
        updateTime,
      </if>
      <if test="userId != null">
        userId,
      </if>
      <if test="userType != null">
        userType,
      </if>
    </trim>
    <trim prefix="values (" suffix=")" suffixOverrides=",">
      <if test="acctId != null">
        #{acctId,jdbcType=INTEGER},
      </if>
      <if test="wjIdentity != null">
        #{wjIdentity,jdbcType=VARCHAR},
      </if>
      <if test="createTime != null">
        #{createTime,jdbcType=TIMESTAMP},
      </if>
      <if test="updateTime != null">
        #{updateTime,jdbcType=TIMESTAMP},
      </if>
      <if test="userId != null">
        #{userId,jdbcType=INTEGER},
      </if>
      <if test="userType != null">
        #{userType,jdbcType=TINYINT},
      </if>
    </trim>
  </insert>
  <update id="update" parameterType="com.mogoroom.service.acct.domain.Account">
    update acct_account
    <set>
      <if test="acctId != null">
        acctId = #{acctId,jdbcType=INTEGER},
      </if>
      <if test="wjIdentity != null">
        wjIdentity = #{wjIdentity,jdbcType=VARCHAR},
      </if>
      <if test="createTime != null">
        createTime = #{createTime,jdbcType=TIMESTAMP},
      </if>
      <if test="updateTime != null">
        updateTime = #{updateTime,jdbcType=TIMESTAMP},
      </if>
      <if test="userId != null">
        userId = #{userId,jdbcType=INTEGER},
      </if>
      <if test="userType != null">
        userType = #{userType,jdbcType=TINYINT},
      </if>
    </set>
    where id = #{id,jdbcType=INTEGER}
  </update>
  <select id="selectAll" resultMap="BaseResultMap">
    select
    <include refid="Base_Column_List" />
    from acct_account
  </select>

  <select id="selectListPageInfo" parameterType="map" resultMap="BaseResultMap">
    select
    <include refid="Base_Column_List" />
    from acct_account
	where 1=1
	    <if test="po.id != null">
          and id = #{po.id,jdbcType=INTEGER}
    </if>
    <if test="po.acctId != null">
          and acctId = #{po.acctId,jdbcType=INTEGER}
    </if>
    <if test="po.wjIdentity != null">
          and wjIdentity = #{po.wjIdentity,jdbcType=VARCHAR}
    </if>
    <if test="po.createTime != null">
          and createTime = #{po.createTime,jdbcType=TIMESTAMP}
    </if>
    <if test="po.updateTime != null">
          and updateTime = #{po.updateTime,jdbcType=TIMESTAMP}
    </if>
    <if test="po.userId != null">
          and userId = #{po.userId,jdbcType=INTEGER}
    </if>
    <if test="po.userType != null">
          and userType = #{po.userType,jdbcType=TINYINT}
    </if>

  </select>

</mapper>